[{"relevance":0,"id":"6weCkLEcKvFf6DTPVB","title":"RSP & Thomax","description":"Sourced from predicthq.com","category":"concerts","labels":["concert","music"],"rank":42,"local_rank":100,"phq_attendance":401,"entities":[],"duration":0,"start":"2024-09-21T17:00:00Z","start_local":"2024-09-21T19:00:00","end":"2024-09-21T17:00:00Z","end_local":"2024-09-21T19:00:00","predicted_end":"2024-09-21T21:30:00Z","predicted_end_local":"2024-09-21T23:30:00","updated":"2024-06-11T02:39:05Z","first_seen":"2024-05-09T04:16:12Z","timezone":"Arctic/Longyearbyen","location":[15.62672,78.22317],"geo":{"geometry":{"coordinates":[15.62672,78.22317],"type":"Point"},"placekey":"@abh-7m3-g6k","address":{"country_code":"SJ","formatted_address":"9170 Longyearbyen, Norway","locality":"Longyearbyen","postcode":"9170","region":"Svalbard"}},"impact_patterns":[{"vertical":"accommodation","impact_type":"phq_attendance","impacts":[{"date_local":"2024-09-21","value":401,"position":"event_day"}]},{"vertical":"hospitality","impact_type":"phq_attendance","impacts":[{"date_local":"2024-09-20","value":61,"position":"leading"},{"date_local":"2024-09-21","value":401,"position":"event_day"},{"date_local":"2024-09-22","value":13,"position":"lagging"}]},{"vertical":"retail","impact_type":"phq_attendance","impacts":[{"date_local":"2024-09-21","value":401,"position":"event_day"}]}],"scope":"locality","country":"SJ","place_hierarchies":[["6295630","6255148","3144096","607072","7521757","7535696","2729907"]],"state":"active","brand_safe":true,"private":false,"predicted_event_spend":16636,"predicted_event_spend_industries":{"accommodation":2132,"hospitality":8597,"transportation":5906},"phq_labels":[{"label":"hip-hop-and-rnb-and-soul","weight":1}]},{"relevance":0,"id":"DFoHFS3UVxSkLt3TgG","title":"MUSIC for ISOLATION","description":"Sourced from predicthq.com","category":"concerts","labels":["concert","music"],"rank":42,"local_rank":100,"phq_attendance":401,"entities":[],"duration":0,"start":"2024-06-11T17:00:00Z","start_local":"2024-06-11T19:00:00","end":"2024-06-11T17:00:00Z","end_local":"2024-06-11T19:00:00","predicted_end":"2024-06-11T21:10:00Z","predicted_end_local":"2024-06-11T23:10:00","updated":"2024-06-25T17:49:12Z","first_seen":"2024-05-24T04:34:58Z","timezone":"Arctic/Longyearbyen","location":[15.62672,78.22317],"geo":{"geometry":{"coordinates":[15.62672,78.22317],"type":"Point"},"placekey":"@abh-7m3-g6k","address":{"country_code":"SJ","formatted_address":"9170 Longyearbyen, Norway","locality":"Longyearbyen","postcode":"9170","region":"Svalbard"}},"impact_patterns":[{"vertical":"accommodation","impact_type":"phq_attendance","impacts":[{"date_local":"2024-06-11","value":401,"position":"event_day"}]},{"vertical":"hospitality","impact_type":"phq_attendance","impacts":[{"date_local":"2024-06-10","value":61,"position":"leading"},{"date_local":"2024-06-11","value":401,"position":"event_day"},{"date_local":"2024-06-12","value":13,"position":"lagging"}]},{"vertical":"retail","impact_type":"phq_attendance","impacts":[{"date_local":"2024-06-11","value":401,"position":"event_day"}]}],"scope":"locality","country":"SJ","place_hierarchies":[["6295630","6255148","3144096","607072","7521757","7535696","2729907"]],"state":"active","brand_safe":true,"private":false,"predicted_event_spend":16636,"predicted_event_spend_industries":{"accommodation":2132,"hospitality":8597,"transportation":5906}},{"relevance":0,"id":"DZd2DmxU5EyWMvKVhv","title":"MUSIC for ISOLATION","description":"Sourced from predicthq.com","category":"concerts","labels":["concert","music"],"rank":42,"local_rank":100,"phq_attendance":401,"entities":[],"duration":0,"start":"2024-06-05T17:00:00Z","start_local":"2024-06-05T19:00:00","end":"2024-06-05T17:00:00Z","end_local":"2024-06-05T19:00:00","predicted_end":"2024-06-05T21:10:00Z","predicted_end_local":"2024-06-05T23:10:00","updated":"2024-06-19T17:29:55Z","first_seen":"2024-05-24T04:36:45Z","timezone":"Arctic/Longyearbyen","location":[15.62672,78.22317],"geo":{"geometry":{"coordinates":[15.62672,78.22317],"type":"Point"},"placekey":"@abh-7m3-g6k","address":{"country_code":"SJ","formatted_address":"9170 Longyearbyen, Norway","locality":"Longyearbyen","postcode":"9170","region":"Svalbard"}},"impact_patterns":[{"vertical":"accommodation","impact_type":"phq_attendance","impacts":[{"date_local":"2024-06-05","value":401,"position":"event_day"}]},{"vertical":"hospitality","impact_type":"phq_attendance","impacts":[{"date_local":"2024-06-04","value":61,"position":"leading"},{"date_local":"2024-06-05","value":401,"position":"event_day"},{"date_local":"2024-06-06","value":13,"position":"lagging"}]},{"vertical":"retail","impact_type":"phq_attendance","impacts":[{"date_local":"2024-06-05","value":401,"position":"event_day"}]}],"scope":"locality","country":"SJ","place_hierarchies":[["6295630","6255148","3144096","607072","7521757","7535696","2729907"]],"state":"active","brand_safe":true,"private":false,"predicted_event_spend":16636,"predicted_event_spend_industries":{"accommodation":2132,"hospitality":8597,"transportation":5906}},{"relevance":0,"id":"7jZZhao8M47ipKQ2bW","title":"Spitsbergen Marathon","description":"Sourced from predicthq.com","category":"sports","labels":["marathon","outdoor-sports","running","sport"],"rank":30,"local_rank":93,"phq_attendance":99,"entities":[],"duration":0,"start":"2024-06-01T08:00:00Z","start_local":"2024-06-01T10:00:00","end":"2024-06-01T08:00:00Z","end_local":"2024-06-01T10:00:00","updated":"2024-05-31T23:12:43Z","first_seen":"2023-08-04T00:07:49Z","timezone":"Arctic/Longyearbyen","location":[15.55,78.216667],"geo":{"geometry":{"coordinates":[15.55,78.216667],"type":"Point"},"placekey":"@abh-7kx-nyv","address":{"country_code":"SJ","formatted_address":"9170 Longyearbyen, Norway","locality":"Longyearbyen","postcode":"9170","region":"Svalbard"}},"impact_patterns":[{"vertical":"accommodation","impact_type":"phq_attendance","impacts":[{"date_local":"2024-06-01","value":99,"position":"event_day"}]},{"vertical":"hospitality","impact_type":"phq_attendance","impacts":[{"date_local":"2024-06-01","value":99,"position":"event_day"}]},{"vertical":"retail","impact_type":"phq_attendance","impacts":[{"date_local":"2024-06-01","value":99,"position":"event_day"}]}],"scope":"locality","country":"SJ","place_hierarchies":[["6295630","6255148","3144096","607072","7521757","7535696","2730733"],["6295630","6255148","3144096","607072","7521757","7535696","2729907"]],"state":"active","brand_safe":true,"private":false,"predicted_event_spend":2864,"predicted_event_spend_industries":{"accommodation":0,"hospitality":1698,"transportation":1166},"phq_labels":[{"label":"marathon","weight":0.33},{"label":"outdoor-sports","weight":0.33},{"label":"running","weight":0.33}]}]